Metadata-Version: 2.1
Name: kernel-knockoffs
Version: 0.1
Summary: Kernel-based knockoff procedure.
Home-page: https://github.com/hclimente/kernel_knockoffs
Author: Héctor Climente-González
Author-email: hector.climente@riken.jp
License: GPL-3
Keywords: fdr,feature_selection,kernel,knockoffs,hsic,mmd
Platform: UNKNOWN
Classifier: Development Status :: 3 - Alpha
Classifier: Topic :: Scientific/Engineering :: Mathematics
Classifier: Intended Audience :: Science/Research
Classifier: License :: OSI Approved :: GNU General Public License v3 (GPLv3)
Classifier: Operating System :: OS Independent
Classifier: Programming Language :: Python :: 3 :: Only
License-File: LICENSE
